setup.py
knights/__init__.py
knights/astlib.py
knights/compiler.py
knights/context.py
knights/dj.py
knights/escape.py
knights/helpers.py
knights/lexer.py
knights/library.py
knights/loader.py
knights/parser.py
knights/tags.py
knights/utils.py
knights/compat/__init__.py
knights/compat/django.py
knights_templater.egg-info/PKG-INFO
knights_templater.egg-info/SOURCES.txt
knights_templater.egg-info/dependency_links.txt
knights_templater.egg-info/top_level.txt