Metadata-Version: 1.0
Name: knights-templater
Version: 1.3
Summary: A simple AST-based Python Template engine.
Home-page: http://github.com/funkybob/knights-templater/
Author: Curtis Maloney
Author-email: curtis@tinbrain.net
License: UNKNOWN
Keywords: template
Platform: UNKNOWN
